README.md
setup.py
additionals/__init__.py
additionals/check_ip.py
additionals/decos.py
additionals/errors.py
additionals/server_descriptor.py
additionals/server_meta.py
additionals/settings.py
additionals/utils.py
log/__init__.py
server/__init__.py
server/server.py
server/server_database.py
server/server_gui.py
server_mess_is_that_joke.egg-info/PKG-INFO
server_mess_is_that_joke.egg-info/SOURCES.txt
server_mess_is_that_joke.egg-info/dependency_links.txt
server_mess_is_that_joke.egg-info/requires.txt
server_mess_is_that_joke.egg-info/top_level.txt
test/__init__.py
test/test_server.py
test/test_utils.py